mw2mhd/__init__.py
mw2mhd/config.py
mw2mhd/convertor_factory.py
mw2mhd/commands/__init__.py
mw2mhd/commands/cli.py
mw2mhd/commands/create.py
mw2mhd/commands/create_mhd_file.py
mw2mhd/commands/fetch_mw_study.py
mw2mhd/commands/validate.py
mw2mhd/v0_1/__init__.py
mw2mhd/v0_1/legacy/__init__.py
mw2mhd/v0_1/legacy/builder.py
mw2mhd/v0_1/legacy/convertor.py
mw2mhd/v0_1/legacy/mw_utils.py
mw2mhd/v0_1/ms/__init__.py
mw2mhd/v0_1/ms/convertor.py
mw_mhd_integration-0.0.13.dist-info/licenses/LICENSE
mw_mhd_integration-0.0.13.dist-info/METADATA
mw_mhd_integration-0.0.13.dist-info/WHEEL
mw_mhd_integration-0.0.13.dist-info/entry_points.txt
mw_mhd_integration-0.0.13.dist-info/top_level.txt
mw_mhd_integration-0.0.13.dist-info/RECORD
