Metadata-Version: 2.4
Name: mw-mhd-integration
Version: 0.0.13
Summary: Metabolomics Workbench - Metabolomics Hub Integration
Author-email: Metabolomics Workbench Team <help@metabolomicsworkbench.org>
License-Expression: Apache-2.0
Requires-Python: >=3.12
License-File: LICENSE
Requires-Dist: mhd-model>=0.1.30
Requires-Dist: pydantic>=2.11.7
Requires-Dist: pydantic-settings>=2.10.1
Requires-Dist: xmltodict>=0.15.1
Dynamic: license-file
